{
    "metadata": {
        "template_id": "barclays_statement_template",
        "version": "1.0.0"
    },
    "rules": [
        {
            "rule_id": "sort_code",
            "type": "form",
            "config": {
                "field_name": "sort_code",
                "coordinates": {
                    "top_left": {
                        "x": 0.641,
                        "y": 0.495
                    },
                    "bottom_right": {
                        "x": 0.7,
                        "y": 0.507
                    }
                },
                "type": "text"
            }
        },
        {
            "rule_id": "account_number",
            "type": "form",
            "config": {
                "field_name": "account_number",
                "coordinates": {
                    "top_left": { "x": 0.550299, "y": 0.604435 },
                    "bottom_right": { "x": 0.602451, "y": 0.620161 }
                },
                "type": "text"
            }
        },
        {
            "rule_id": "customer_name",
            "type": "form",
            "config": {
                "field_name": "customer_name",
                "coordinates": {
                    "top_left": { "x": 0.412653, "y": 0.679839 },
                    "bottom_right": { "x": 0.550299, "y": 0.697984 }
                },
                "type": "text"
            }
        },
        {
            "rule_id": "start_balance",
            "type": "form",
            "config": {
                "field_name": "start_balance",
                "coordinates": {
                    "top_left": { "x": 0.61271, "y": 0.267742 },
                    "bottom_right": { "x": 0.661157, "y": 0.283871 }
                },
                "type": "text"
            }
        },
        {
            "rule_id": "money_in",
            "type": "form",
            "config": {
                "field_name": "money_in",
                "coordinates": {
                    "top_left": { "x": 0.61271, "y": 0.295161 },
                    "bottom_right": { "x": 0.669137, "y": 0.312903 }
                },
                "type": "text"
            }
        },
        {
            "rule_id": "money_out",
            "type": "form",
            "config": {
                "field_name": "money_out",
                "coordinates": {
                    "top_left": { "x": 0.61271, "y": 0.320565 },
                    "bottom_right": { "x": 0.669137, "y": 0.338306 }
                },
                "type": "text"
            }
        },
        {
            "rule_id": "end_balance",
            "type": "form",
            "config": {
                "field_name": "end_balance",
                "coordinates": {
                    "top_left": { "x": 0.61271, "y": 0.346371 },
                    "bottom_right": { "x": 0.661157, "y": 0.3625 }
                },
                "type": "text"
            }
        },
        {
            "rule_id": "overdraft_limit",
            "type": "form",
            "config": {
                "field_name": "overdraft_limit",
                "coordinates": {
                    "top_left": { "x": 0.626959, "y": 0.421371 },
                    "bottom_right": { "x": 0.668282, "y": 0.438306 }
                },
                "type": "text"
            }
        },
        {
            "rule_id": "transactions_page_2_onwards",
            "type": "table",
            "config": {
                "columns": [
                    {
                        "field_name": "date",
                        "coordinates": {
                            "top_left": {
                                "x": 0.097,
                                "y": 0.488
                            },
                            "bottom_right": {
                                "x": 0.149,
                                "y": 0.898
                            }
                        },
                        "type": "text"
                    },
                    {
                        "field_name": "description",
                        "coordinates": {
                            "top_left": { "x": 0.128527, "y": 0.690323 },
                            "bottom_right": { "x": 0.300085, "y": 1.02621 }
                        },
                        "type": "text"
                    },
                    {
                        "field_name": "money_in",
                        "coordinates": {
                            "top_left": { "x": 0.30778, "y": 0.690323 },
                            "bottom_right": { "x": 0.345398, "y": 1.02621 }
                        },
                        "type": "text"
                    },
                    {
                        "field_name": "money_out",
                        "coordinates": {
                            "top_left": { "x": 0.364776, "y": 0.690323 },
                            "bottom_right": { "x": 0.402394, "y": 1.02621 }
                        },
                        "type": "text"
                    },
                    {
                        "field_name": "balance",
                        "coordinates": {
                            "top_left": { "x": 0.427472, "y": 0.690323 },
                            "bottom_right": { "x": 0.46509, "y": 1.02621 }
                        },
                        "type": "text"
                    }
                ],
                "row_delimiter": {
                    "type": "line"
                }
            }
        }
    ],
    "pages": [
        {
            "page_numbers": ["1"],
            "forms": ["customer_details", "sort_code", "account_number"]
        },
        {
            "page_numbers": ["2"],
            "forms": ["start_balance", "money_in", "money_out", "end_balance", "overdraft_limit"]
        },
        {
            "page_numbers": ["2-(-2)"],
            "forms": [],
            "tables": ["transactions_page_2_onwards"]
        },
        {
            "page_numbers": ["-1"],
            "ignore": true
        }
    ]
}