{
    "pdf_plumber_words": [
        "bacs",
        "employee",
        "pay",
        "hiyacar",
        "tax",
        "td",
        "ni",
        "burns",
        "pension",
        "crescent",
        "paid",
        "avc",
        "bicester",
        "pensioninctd",
        "gross",
        "employer",
        "oxfordshire",
        "for",
        "salary",
        "jake",
        "national",
        "payment",
        "insurance",
        "apc",
        "holidays",
        "total",
        "limited",
        "earnings",
        "paye",
        "holmes",
        "monthly"
    ],
    "pytesseract_words": [
        "al",
        "apcs",
        "iisurainee",
        "ee",
        "payments",
        "te",
        "apl",
        "a",
        "oan",
        "neto",
        "amount",
        "xa",
        "psou",
        "notbarnal",
        "tetal",
        "sa",
        "pension",
        "poy",
        "pee",
        "hacer",
        "persp",
        "emploger",
        "gross",
        "fs",
        "de",
        "for",
        "arene",
        "lie",
        "insurance",
        "avion",
        "ay",
        "nolbonal",
        "eimitck",
        "ou",
        "carass",
        "alien",
        "grass",
        "lvacar",
        "ag",
        "poe",
        "sl",
        "units",
        "far",
        "paye",
        "ine",
        "avtd",
        "monthly",
        "oo",
        "date",
        "year",
        "lyegar",
        "ponsion",
        "tax",
        "apio",
        "td",
        "req",
        "burns",
        "ni",
        "dislaf",
        "emplover",
        "rate",
        "bor",
        "poi",
        "oxfordshire",
        "pq",
        "diiny",
        "etnies",
        "national",
        "di",
        "tas",
        "eniplover",
        "empkven",
        "pry",
        "apc",
        "holidays",
        "iy",
        "pao",
        "vats",
        "apch",
        "netd",
        "pensionine",
        "of",
        "creseent",
        "employee",
        "paoclcu",
        "faross",
        "pay",
        "tred",
        "notional",
        "oe",
        "q",
        "sens",
        "crescent",
        "cn",
        "number",
        "pyeewainl",
        "wetd",
        "tata",
        "employer",
        "ml",
        "sop",
        "en",
        "con",
        "pony",
        "hivacar",
        "peonspar",
        "earns",
        "ae",
        "jake",
        "tay",
        "period",
        "ban",
        "name",
        "this",
        "md",
        "cee",
        "my",
        "talal",
        "employes",
        "bs",
        "to",
        "eee",
        "yy",
        "limited",
        "tra",
        "penstanine",
        "earnings",
        "epartmmene",
        "emploves",
        "wet",
        "empleyeor",
        "anal",
        "bacs",
        "pog",
        "earrnineys",
        "pso",
        "an",
        "iisurance",
        "bicester",
        "plast",
        "porsboan",
        "pout",
        "dine",
        "den",
        "insurances",
        "process",
        "fatal",
        "salary",
        "ayo",
        "payment",
        "metd",
        "pag",
        "bar",
        "pensiontne",
        "earnineys",
        "aan",
        "erriplover",
        "say",
        "on",
        "ps",
        "oxa",
        "deductions",
        "re",
        "capass",
        "holmes",
        "saf",
        "gress"
    ],
    "pdf_plumber_recognized_count": 18,
    "pytesseract_recognized_count": 70,
    "pdf_plumber_brand_count": 0,
    "pytesseract_brand_count": 0,
    "pdf_plumber_city_count": 0,
    "pytesseract_city_count": 0
}